threedi_cmd_statistics/__init__.py
threedi_cmd_statistics/console.py
threedi_cmd_statistics/logger.py
threedi_cmd_statistics/models.py
threedi_cmd_statistics/commands/__init__.py
threedi_cmd_statistics/commands/app_definitions.py
threedi_cmd_statistics/commands/apps.py
threedi_cmd_statistics/commands/callbacks.py
threedi_cmd_statistics/commands/main.py
threedi_cmd_statistics/commands/models.py
threedi_cmd_statistics/http/__init__.py
threedi_cmd_statistics/http/clients.py
threedi_cmd_statistics/http/tools.py
threedi_cmd_statistics/plots/__init__.py
threedi_cmd_statistics/plots/rich/__init__.py
threedi_cmd_statistics/plots/rich/customers.py
threedi_cmd_statistics/plots/rich/exit_codes.py
threedi_cmd_statistics/plots/rich/sessions.py
threedi_cmd_statistics/plots/rich/usage.py
threedi_cmd_statistics/statistics/__init__.py
threedi_cmd_statistics/statistics/customers.py
threedi_cmd_statistics/statistics/models.py
threedi_cmd_statistics/statistics/sessions.py
threedi_cmd_statistics/statistics/tools.py
threedi_cmd_statistics/statistics/usage.py
threedi_cmd_statistics/validators/__init__.py
threedi_cmd_statistics/validators/dates.py
threedi_cmd_statistics/validators/models.py
threedi_cmd_statistics/validators/strings.py
threedi_cmd_statistics-0.0.5.dist-info/AUTHORS.rst
threedi_cmd_statistics-0.0.5.dist-info/LICENSE
threedi_cmd_statistics-0.0.5.dist-info/METADATA
threedi_cmd_statistics-0.0.5.dist-info/WHEEL
threedi_cmd_statistics-0.0.5.dist-info/entry_points.txt
threedi_cmd_statistics-0.0.5.dist-info/top_level.txt
threedi_cmd_statistics-0.0.5.dist-info/RECORD
