Metadata-Version: 2.1
Name: threedi-cmd-statistics
Version: 0.0.5
Summary: Statistics plugin for the 3Di cmd client
Home-page: https://github.com/nens/threedi-cmd-statistics
Author: Lars Claussen
Author-email: claussen.lars@nelen-schuurmans.nl
License: MIT license
Keywords: threedi_api_stats
Platform: UNKNOWN
Classifier: Development Status :: 2 - Pre-Alpha
Classifier: Intended Audience :: Developers
Classifier: License :: OSI Approved :: MIT License
Classifier: Natural Language :: English
Classifier: Programming Language :: Python :: 3
Classifier: Programming Language :: Python :: 3.8
Classifier: Programming Language :: Python :: 3.9
Requires-Python: >=3.8
Requires-Dist: rich (>=9.4.0)
Requires-Dist: typer (>=0.3.2)
Requires-Dist: threedi-api-client (>=3.0.21)
